{"collection":"mon","name":"eventMap","columnValue":"","description":"Event Map for LO agent","outputFile":"{AGENT}_eventmap.map","content":"<itmEventMapping:agent>\r\t<event_mapping>\n<tkBookmark collection=\"event\" name=\"agent\" column=\"AGENT\" />\n\t</event_mapping>\r</itmEventMapping:agent>","directives":[{"type":10,"softFail":false,"description":"Insert Event Mappings for Situations","notLast":[],"onlyLast":[],"provider":{"type":1,"source":"tiaDB","columns":"*","from":"ITM6_CONFIG","where":"PROFILE IN ({PROFILES}) AND AGENT = '{AGENT}'"}}]}