{"collection":"system","name":"default","columnValue":"","description":"The Default Template","outputFile":"","content":"\u003chtml\u003e\n\u003chead\u003e\u003c/head\u003e\n\u003cbody\u003e\n    \u003cp\u003eThis is the Default Template used when a merge request fails to provide the template name in the DragonFlyFullName parameter.\u003c/p\u003e\n    \u003cp\u003eTo invoke a merge of a specific template call /idmu/merge?DragonFlyFullName\u003dyour.template.name \u003c/p\u003e\n    \u003cp\u003ePlease note that both periods are required, so the template name system.default is invalid, but system.default. is valid.\u003c/p\u003e\n\u003c/body\u003e\n\u003c/html\u003e","directives":[]}